tksbrokerapi/TKSBrokerAPI.py
tksbrokerapi/TKSEnums.py
tksbrokerapi/Templates.py
tksbrokerapi/TradeRoutines.py
tksbrokerapi/UniLogger.py
tksbrokerapi/__init__.py
tksbrokerapi/__main__.py
tksbrokerapi/_version.py
tksbrokerapi-1.6.268.dist-info/LICENSE
tksbrokerapi-1.6.268.dist-info/METADATA
tksbrokerapi-1.6.268.dist-info/WHEEL
tksbrokerapi-1.6.268.dist-info/entry_points.txt
tksbrokerapi-1.6.268.dist-info/top_level.txt
tksbrokerapi-1.6.268.dist-info/zip-safe
tksbrokerapi-1.6.268.dist-info/RECORD
