Metadata-Version: 2.1
Name: tksbrokerapi
Version: 1.6.268
Summary: TKSBrokerAPI is a trading platform designed to automate and simplify trading scenarios. It integrates with the Tinkoff Invest API server using the REST protocol. The platform can be used in two flexible ways: Command-Line Interface (CLI) and Python Library. This feature-rich API is perfect for trading enthusiasts and professional developers creating advanced automation solutions.
Home-page: https://github.com/Tim55667757/TKSBrokerAPI/
Author: Timur Gilmullin
Author-email: tim55667757@gmail.com
License: Apache-2.0
Download-URL: https://github.com/Tim55667757/TKSBrokerAPI.git
Keywords: history,csv,stock,prices,candlesticks,statistics,cli,client,rest,rest-api,api-client,trading-api,trading,trading-platform,trade,tinkoff,tinkoff-api,python-api,openapi,platform
Platform: UNKNOWN
Classifier: Development Status :: 5 - Production/Stable
Classifier: Environment :: Console
Classifier: Intended Audience :: Financial and Insurance Industry
Classifier: Topic :: Utilities
Classifier: License :: OSI Approved :: Apache Software License
Classifier: Natural Language :: English
Classifier: Programming Language :: Python :: 3
Requires-Python: >=3.9
License-File: LICENSE
Requires-Dist: numpy>=1.23.5
Requires-Dist: scipy>=1.13.1
Requires-Dist: numba>=0.59.1
Requires-Dist: llvmlite>=0.42.0
Requires-Dist: pandas>=2.2.3
Requires-Dist: requests>=2.32.0
Requires-Dist: openpyxl>=3.0.10
Requires-Dist: Mako>=1.2.4
Requires-Dist: python-dateutil>=2.8.1
Requires-Dist: pycron>=3.0.0
Requires-Dist: PriceGenerator>=1.4.93
Requires-Dist: FuzzyRoutines>=1.0.3
